{
  "title": "Morning Lobby Rush",
  "profile": "DOWN_PEAK",
  "arrival_rate": 0.25,
  "seed": 42,
  "max_ticks": 50,
  "heuristic": {
    "events": [
      {
        "event_type": "PassengerSpawned",
        "message": "[002 T] PASSENGER_SPAWNED: P1 requests 3->0",
        "time": 2,
        "passenger_id": "P1",
        "source": 3,
        "target": 0
      },
      {
        "event_type": "CallRegistered",
        "message": "[002 T] CALL_REGISTERED: Floor 3 requests DOWN",
        "time": 2,
        "floor": 3,
        "direction": -1
      },
      {
        "event_type": "PassengerSpawned",
        "message": "[003 T] PASSENGER_SPAWNED: P2 requests 2->0",
        "time": 3,
        "passenger_id": "P2",
        "source": 2,
        "target": 0
      },
      {
        "event_type": "CallRegistered",
        "message": "[003 T] CALL_REGISTERED: Floor 2 requests DOWN",
        "time": 3,
        "floor": 2,
        "direction": -1
      },
      {
        "event_type": "CarMoved",
        "message": "[003 T] CAR_MOVED: Car C1 traveled 0 -> 1",
        "time": 3,
        "car_id": "C1",
        "from_floor": 0,
        "to_floor": 1
      },
      {
        "event_type": "CarMoved",
        "message": "[004 T] CAR_MOVED: Car C1 traveled 1 -> 2",
        "time": 4,
        "car_id": "C1",
        "from_floor": 1,
        "to_floor": 2
      },
      {
        "event_type": "CarMoved",
        "message": "[005 T] CAR_MOVED: Car C1 traveled 2 -> 3",
        "time": 5,
        "car_id": "C1",
        "from_floor": 2,
        "to_floor": 3
      },
      {
        "event_type": "CarArrived",
        "message": "[005 T] CAR_ARRIVED: Car C1 arrived at floor 3",
        "time": 5,
        "car_id": "C1",
        "floor": 3
      },
      {
        "event_type": "DoorOpened",
        "message": "[005 T] DOOR_OPENED: Car C1 opened doors at floor 3",
        "time": 5,
        "car_id": "C1",
        "floor": 3
      },
      {
        "event_type": "PassengerBoarded",
        "message": "[005 T] PASSENGER_BOARDED: P1 boarded car C1 at floor 3",
        "time": 5,
        "passenger_id": "P1",
        "car_id": "C1",
        "floor": 3
      },
      {
        "event_type": "PassengerSpawned",
        "message": "[007 T] PASSENGER_SPAWNED: P3 requests 4->0",
        "time": 7,
        "passenger_id": "P3",
        "source": 4,
        "target": 0
      },
      {
        "event_type": "CallRegistered",
        "message": "[007 T] CALL_REGISTERED: Floor 4 requests DOWN",
        "time": 7,
        "floor": 4,
        "direction": -1
      },
      {
        "event_type": "DoorClosed",
        "message": "[007 T] DOOR_CLOSED: Car C1 closed doors at floor 3",
        "time": 7,
        "car_id": "C1",
        "floor": 3
      },
      {
        "event_type": "PassengerSpawned",
        "message": "[008 T] PASSENGER_SPAWNED: P4 requests 1->0",
        "time": 8,
        "passenger_id": "P4",
        "source": 1,
        "target": 0
      },
      {
        "event_type": "CallRegistered",
        "message": "[008 T] CALL_REGISTERED: Floor 1 requests DOWN",
        "time": 8,
        "floor": 1,
        "direction": -1
      },
      {
        "event_type": "CarMoved",
        "message": "[008 T] CAR_MOVED: Car C1 traveled 3 -> 4",
        "time": 8,
        "car_id": "C1",
        "from_floor": 3,
        "to_floor": 4
      },
      {
        "event_type": "CarArrived",
        "message": "[008 T] CAR_ARRIVED: Car C1 arrived at floor 4",
        "time": 8,
        "car_id": "C1",
        "floor": 4
      },
      {
        "event_type": "DoorOpened",
        "message": "[008 T] DOOR_OPENED: Car C1 opened doors at floor 4",
        "time": 8,
        "car_id": "C1",
        "floor": 4
      },
      {
        "event_type": "PassengerBoarded",
        "message": "[008 T] PASSENGER_BOARDED: P3 boarded car C1 at floor 4",
        "time": 8,
        "passenger_id": "P3",
        "car_id": "C1",
        "floor": 4
      },
      {
        "event_type": "PassengerSpawned",
        "message": "[009 T] PASSENGER_SPAWNED: P5 requests 1->0",
        "time": 9,
        "passenger_id": "P5",
        "source": 1,
        "target": 0
      },
      {
        "event_type": "CallRegistered",
        "message": "[009 T] CALL_REGISTERED: Floor 1 requests DOWN",
        "time": 9,
        "floor": 1,
        "direction": -1
      },
      {
        "event_type": "DoorClosed",
        "message": "[010 T] DOOR_CLOSED: Car C1 closed doors at floor 4",
        "time": 10,
        "car_id": "C1",
        "floor": 4
      },
      {
        "event_type": "CarMoved",
        "message": "[011 T] CAR_MOVED: Car C1 traveled 4 -> 3",
        "time": 11,
        "car_id": "C1",
        "from_floor": 4,
        "to_floor": 3
      },
      {
        "event_type": "CarMoved",
        "message": "[012 T] CAR_MOVED: Car C1 traveled 3 -> 2",
        "time": 12,
        "car_id": "C1",
        "from_floor": 3,
        "to_floor": 2
      },
      {
        "event_type": "CarArrived",
        "message": "[012 T] CAR_ARRIVED: Car C1 arrived at floor 2",
        "time": 12,
        "car_id": "C1",
        "floor": 2
      },
      {
        "event_type": "DoorOpened",
        "message": "[012 T] DOOR_OPENED: Car C1 opened doors at floor 2",
        "time": 12,
        "car_id": "C1",
        "floor": 2
      },
      {
        "event_type": "PassengerBoarded",
        "message": "[012 T] PASSENGER_BOARDED: P2 boarded car C1 at floor 2",
        "time": 12,
        "passenger_id": "P2",
        "car_id": "C1",
        "floor": 2
      },
      {
        "event_type": "DoorClosed",
        "message": "[014 T] DOOR_CLOSED: Car C1 closed doors at floor 2",
        "time": 14,
        "car_id": "C1",
        "floor": 2
      },
      {
        "event_type": "CarMoved",
        "message": "[015 T] CAR_MOVED: Car C1 traveled 2 -> 1",
        "time": 15,
        "car_id": "C1",
        "from_floor": 2,
        "to_floor": 1
      },
      {
        "event_type": "CarArrived",
        "message": "[015 T] CAR_ARRIVED: Car C1 arrived at floor 1",
        "time": 15,
        "car_id": "C1",
        "floor": 1
      },
      {
        "event_type": "DoorOpened",
        "message": "[015 T] DOOR_OPENED: Car C1 opened doors at floor 1",
        "time": 15,
        "car_id": "C1",
        "floor": 1
      },
      {
        "event_type": "PassengerBoarded",
        "message": "[015 T] PASSENGER_BOARDED: P4 boarded car C1 at floor 1",
        "time": 15,
        "passenger_id": "P4",
        "car_id": "C1",
        "floor": 1
      },
      {
        "event_type": "PassengerBoarded",
        "message": "[015 T] PASSENGER_BOARDED: P5 boarded car C1 at floor 1",
        "time": 15,
        "passenger_id": "P5",
        "car_id": "C1",
        "floor": 1
      },
      {
        "event_type": "DoorClosed",
        "message": "[017 T] DOOR_CLOSED: Car C1 closed doors at floor 1",
        "time": 17,
        "car_id": "C1",
        "floor": 1
      },
      {
        "event_type": "PassengerSpawned",
        "message": "[018 T] PASSENGER_SPAWNED: P6 requests 4->0",
        "time": 18,
        "passenger_id": "P6",
        "source": 4,
        "target": 0
      },
      {
        "event_type": "CallRegistered",
        "message": "[018 T] CALL_REGISTERED: Floor 4 requests DOWN",
        "time": 18,
        "floor": 4,
        "direction": -1
      },
      {
        "event_type": "CarMoved",
        "message": "[018 T] CAR_MOVED: Car C1 traveled 1 -> 0",
        "time": 18,
        "car_id": "C1",
        "from_floor": 1,
        "to_floor": 0
      },
      {
        "event_type": "CarArrived",
        "message": "[018 T] CAR_ARRIVED: Car C1 arrived at floor 0",
        "time": 18,
        "car_id": "C1",
        "floor": 0
      },
      {
        "event_type": "DoorOpened",
        "message": "[018 T] DOOR_OPENED: Car C1 opened doors at floor 0",
        "time": 18,
        "car_id": "C1",
        "floor": 0
      },
      {
        "event_type": "PassengerDeboarded",
        "message": "[018 T] PASSENGER_DEBOARDED: P1 exited car C1 at floor 0",
        "time": 18,
        "passenger_id": "P1",
        "car_id": "C1",
        "floor": 0
      },
      {
        "event_type": "PassengerDeboarded",
        "message": "[018 T] PASSENGER_DEBOARDED: P3 exited car C1 at floor 0",
        "time": 18,
        "passenger_id": "P3",
        "car_id": "C1",
        "floor": 0
      },
      {
        "event_type": "PassengerDeboarded",
        "message": "[018 T] PASSENGER_DEBOARDED: P2 exited car C1 at floor 0",
        "time": 18,
        "passenger_id": "P2",
        "car_id": "C1",
        "floor": 0
      },
      {
        "event_type": "PassengerDeboarded",
        "message": "[018 T] PASSENGER_DEBOARDED: P4 exited car C1 at floor 0",
        "time": 18,
        "passenger_id": "P4",
        "car_id": "C1",
        "floor": 0
      },
      {
        "event_type": "PassengerDeboarded",
        "message": "[018 T] PASSENGER_DEBOARDED: P5 exited car C1 at floor 0",
        "time": 18,
        "passenger_id": "P5",
        "car_id": "C1",
        "floor": 0
      },
      {
        "event_type": "PassengerSpawned",
        "message": "[020 T] PASSENGER_SPAWNED: P7 requests 3->0",
        "time": 20,
        "passenger_id": "P7",
        "source": 3,
        "target": 0
      },
      {
        "event_type": "CallRegistered",
        "message": "[020 T] CALL_REGISTERED: Floor 3 requests DOWN",
        "time": 20,
        "floor": 3,
        "direction": -1
      },
      {
        "event_type": "DoorClosed",
        "message": "[020 T] DOOR_CLOSED: Car C1 closed doors at floor 0",
        "time": 20,
        "car_id": "C1",
        "floor": 0
      },
      {
        "event_type": "PassengerSpawned",
        "message": "[021 T] PASSENGER_SPAWNED: P8 requests 4->0",
        "time": 21,
        "passenger_id": "P8",
        "source": 4,
        "target": 0
      },
      {
        "event_type": "CallRegistered",
        "message": "[021 T] CALL_REGISTERED: Floor 4 requests DOWN",
        "time": 21,
        "floor": 4,
        "direction": -1
      },
      {
        "event_type": "CarMoved",
        "message": "[021 T] CAR_MOVED: Car C1 traveled 0 -> 1",
        "time": 21,
        "car_id": "C1",
        "from_floor": 0,
        "to_floor": 1
      },
      {
        "event_type": "PassengerSpawned",
        "message": "[022 T] PASSENGER_SPAWNED: P9 requests 3->0",
        "time": 22,
        "passenger_id": "P9",
        "source": 3,
        "target": 0
      },
      {
        "event_type": "CallRegistered",
        "message": "[022 T] CALL_REGISTERED: Floor 3 requests DOWN",
        "time": 22,
        "floor": 3,
        "direction": -1
      },
      {
        "event_type": "CarMoved",
        "message": "[022 T] CAR_MOVED: Car C1 traveled 1 -> 2",
        "time": 22,
        "car_id": "C1",
        "from_floor": 1,
        "to_floor": 2
      },
      {
        "event_type": "CarMoved",
        "message": "[023 T] CAR_MOVED: Car C1 traveled 2 -> 3",
        "time": 23,
        "car_id": "C1",
        "from_floor": 2,
        "to_floor": 3
      },
      {
        "event_type": "CarArrived",
        "message": "[023 T] CAR_ARRIVED: Car C1 arrived at floor 3",
        "time": 23,
        "car_id": "C1",
        "floor": 3
      },
      {
        "event_type": "DoorOpened",
        "message": "[023 T] DOOR_OPENED: Car C1 opened doors at floor 3",
        "time": 23,
        "car_id": "C1",
        "floor": 3
      },
      {
        "event_type": "PassengerBoarded",
        "message": "[023 T] PASSENGER_BOARDED: P7 boarded car C1 at floor 3",
        "time": 23,
        "passenger_id": "P7",
        "car_id": "C1",
        "floor": 3
      },
      {
        "event_type": "PassengerBoarded",
        "message": "[023 T] PASSENGER_BOARDED: P9 boarded car C1 at floor 3",
        "time": 23,
        "passenger_id": "P9",
        "car_id": "C1",
        "floor": 3
      },
      {
        "event_type": "DoorClosed",
        "message": "[025 T] DOOR_CLOSED: Car C1 closed doors at floor 3",
        "time": 25,
        "car_id": "C1",
        "floor": 3
      },
      {
        "event_type": "CarMoved",
        "message": "[026 T] CAR_MOVED: Car C1 traveled 3 -> 4",
        "time": 26,
        "car_id": "C1",
        "from_floor": 3,
        "to_floor": 4
      },
      {
        "event_type": "CarArrived",
        "message": "[026 T] CAR_ARRIVED: Car C1 arrived at floor 4",
        "time": 26,
        "car_id": "C1",
        "floor": 4
      },
      {
        "event_type": "DoorOpened",
        "message": "[026 T] DOOR_OPENED: Car C1 opened doors at floor 4",
        "time": 26,
        "car_id": "C1",
        "floor": 4
      },
      {
        "event_type": "PassengerBoarded",
        "message": "[026 T] PASSENGER_BOARDED: P6 boarded car C1 at floor 4",
        "time": 26,
        "passenger_id": "P6",
        "car_id": "C1",
        "floor": 4
      },
      {
        "event_type": "PassengerBoarded",
        "message": "[026 T] PASSENGER_BOARDED: P8 boarded car C1 at floor 4",
        "time": 26,
        "passenger_id": "P8",
        "car_id": "C1",
        "floor": 4
      },
      {
        "event_type": "DoorClosed",
        "message": "[028 T] DOOR_CLOSED: Car C1 closed doors at floor 4",
        "time": 28,
        "car_id": "C1",
        "floor": 4
      },
      {
        "event_type": "CarMoved",
        "message": "[029 T] CAR_MOVED: Car C1 traveled 4 -> 3",
        "time": 29,
        "car_id": "C1",
        "from_floor": 4,
        "to_floor": 3
      },
      {
        "event_type": "CarMoved",
        "message": "[030 T] CAR_MOVED: Car C1 traveled 3 -> 2",
        "time": 30,
        "car_id": "C1",
        "from_floor": 3,
        "to_floor": 2
      },
      {
        "event_type": "CarMoved",
        "message": "[031 T] CAR_MOVED: Car C1 traveled 2 -> 1",
        "time": 31,
        "car_id": "C1",
        "from_floor": 2,
        "to_floor": 1
      },
      {
        "event_type": "CarMoved",
        "message": "[032 T] CAR_MOVED: Car C1 traveled 1 -> 0",
        "time": 32,
        "car_id": "C1",
        "from_floor": 1,
        "to_floor": 0
      },
      {
        "event_type": "CarArrived",
        "message": "[032 T] CAR_ARRIVED: Car C1 arrived at floor 0",
        "time": 32,
        "car_id": "C1",
        "floor": 0
      },
      {
        "event_type": "DoorOpened",
        "message": "[032 T] DOOR_OPENED: Car C1 opened doors at floor 0",
        "time": 32,
        "car_id": "C1",
        "floor": 0
      },
      {
        "event_type": "PassengerDeboarded",
        "message": "[032 T] PASSENGER_DEBOARDED: P7 exited car C1 at floor 0",
        "time": 32,
        "passenger_id": "P7",
        "car_id": "C1",
        "floor": 0
      },
      {
        "event_type": "PassengerDeboarded",
        "message": "[032 T] PASSENGER_DEBOARDED: P9 exited car C1 at floor 0",
        "time": 32,
        "passenger_id": "P9",
        "car_id": "C1",
        "floor": 0
      },
      {
        "event_type": "PassengerDeboarded",
        "message": "[032 T] PASSENGER_DEBOARDED: P6 exited car C1 at floor 0",
        "time": 32,
        "passenger_id": "P6",
        "car_id": "C1",
        "floor": 0
      },
      {
        "event_type": "PassengerDeboarded",
        "message": "[032 T] PASSENGER_DEBOARDED: P8 exited car C1 at floor 0",
        "time": 32,
        "passenger_id": "P8",
        "car_id": "C1",
        "floor": 0
      },
      {
        "event_type": "DoorClosed",
        "message": "[034 T] DOOR_CLOSED: Car C1 closed doors at floor 0",
        "time": 34,
        "car_id": "C1",
        "floor": 0
      },
      {
        "event_type": "PassengerSpawned",
        "message": "[035 T] PASSENGER_SPAWNED: P10 requests 2->0",
        "time": 35,
        "passenger_id": "P10",
        "source": 2,
        "target": 0
      },
      {
        "event_type": "CallRegistered",
        "message": "[035 T] CALL_REGISTERED: Floor 2 requests DOWN",
        "time": 35,
        "floor": 2,
        "direction": -1
      },
      {
        "event_type": "CarMoved",
        "message": "[036 T] CAR_MOVED: Car C1 traveled 0 -> 1",
        "time": 36,
        "car_id": "C1",
        "from_floor": 0,
        "to_floor": 1
      },
      {
        "event_type": "CarMoved",
        "message": "[037 T] CAR_MOVED: Car C1 traveled 1 -> 2",
        "time": 37,
        "car_id": "C1",
        "from_floor": 1,
        "to_floor": 2
      },
      {
        "event_type": "CarArrived",
        "message": "[037 T] CAR_ARRIVED: Car C1 arrived at floor 2",
        "time": 37,
        "car_id": "C1",
        "floor": 2
      },
      {
        "event_type": "DoorOpened",
        "message": "[037 T] DOOR_OPENED: Car C1 opened doors at floor 2",
        "time": 37,
        "car_id": "C1",
        "floor": 2
      },
      {
        "event_type": "PassengerBoarded",
        "message": "[037 T] PASSENGER_BOARDED: P10 boarded car C1 at floor 2",
        "time": 37,
        "passenger_id": "P10",
        "car_id": "C1",
        "floor": 2
      },
      {
        "event_type": "DoorClosed",
        "message": "[039 T] DOOR_CLOSED: Car C1 closed doors at floor 2",
        "time": 39,
        "car_id": "C1",
        "floor": 2
      },
      {
        "event_type": "CarMoved",
        "message": "[040 T] CAR_MOVED: Car C1 traveled 2 -> 1",
        "time": 40,
        "car_id": "C1",
        "from_floor": 2,
        "to_floor": 1
      },
      {
        "event_type": "CarMoved",
        "message": "[041 T] CAR_MOVED: Car C1 traveled 1 -> 0",
        "time": 41,
        "car_id": "C1",
        "from_floor": 1,
        "to_floor": 0
      },
      {
        "event_type": "CarArrived",
        "message": "[041 T] CAR_ARRIVED: Car C1 arrived at floor 0",
        "time": 41,
        "car_id": "C1",
        "floor": 0
      },
      {
        "event_type": "DoorOpened",
        "message": "[041 T] DOOR_OPENED: Car C1 opened doors at floor 0",
        "time": 41,
        "car_id": "C1",
        "floor": 0
      },
      {
        "event_type": "PassengerDeboarded",
        "message": "[041 T] PASSENGER_DEBOARDED: P10 exited car C1 at floor 0",
        "time": 41,
        "passenger_id": "P10",
        "car_id": "C1",
        "floor": 0
      },
      {
        "event_type": "PassengerSpawned",
        "message": "[043 T] PASSENGER_SPAWNED: P11 requests 3->0",
        "time": 43,
        "passenger_id": "P11",
        "source": 3,
        "target": 0
      },
      {
        "event_type": "CallRegistered",
        "message": "[043 T] CALL_REGISTERED: Floor 3 requests DOWN",
        "time": 43,
        "floor": 3,
        "direction": -1
      },
      {
        "event_type": "DoorClosed",
        "message": "[043 T] DOOR_CLOSED: Car C1 closed doors at floor 0",
        "time": 43,
        "car_id": "C1",
        "floor": 0
      },
      {
        "event_type": "PassengerSpawned",
        "message": "[044 T] PASSENGER_SPAWNED: P12 requests 3->0",
        "time": 44,
        "passenger_id": "P12",
        "source": 3,
        "target": 0
      },
      {
        "event_type": "CallRegistered",
        "message": "[044 T] CALL_REGISTERED: Floor 3 requests DOWN",
        "time": 44,
        "floor": 3,
        "direction": -1
      },
      {
        "event_type": "CarMoved",
        "message": "[044 T] CAR_MOVED: Car C1 traveled 0 -> 1",
        "time": 44,
        "car_id": "C1",
        "from_floor": 0,
        "to_floor": 1
      },
      {
        "event_type": "CarMoved",
        "message": "[045 T] CAR_MOVED: Car C1 traveled 1 -> 2",
        "time": 45,
        "car_id": "C1",
        "from_floor": 1,
        "to_floor": 2
      },
      {
        "event_type": "CarMoved",
        "message": "[046 T] CAR_MOVED: Car C1 traveled 2 -> 3",
        "time": 46,
        "car_id": "C1",
        "from_floor": 2,
        "to_floor": 3
      },
      {
        "event_type": "CarArrived",
        "message": "[046 T] CAR_ARRIVED: Car C1 arrived at floor 3",
        "time": 46,
        "car_id": "C1",
        "floor": 3
      },
      {
        "event_type": "DoorOpened",
        "message": "[046 T] DOOR_OPENED: Car C1 opened doors at floor 3",
        "time": 46,
        "car_id": "C1",
        "floor": 3
      },
      {
        "event_type": "PassengerBoarded",
        "message": "[046 T] PASSENGER_BOARDED: P11 boarded car C1 at floor 3",
        "time": 46,
        "passenger_id": "P11",
        "car_id": "C1",
        "floor": 3
      },
      {
        "event_type": "PassengerBoarded",
        "message": "[046 T] PASSENGER_BOARDED: P12 boarded car C1 at floor 3",
        "time": 46,
        "passenger_id": "P12",
        "car_id": "C1",
        "floor": 3
      },
      {
        "event_type": "PassengerSpawned",
        "message": "[047 T] PASSENGER_SPAWNED: P13 requests 2->0",
        "time": 47,
        "passenger_id": "P13",
        "source": 2,
        "target": 0
      },
      {
        "event_type": "CallRegistered",
        "message": "[047 T] CALL_REGISTERED: Floor 2 requests DOWN",
        "time": 47,
        "floor": 2,
        "direction": -1
      },
      {
        "event_type": "DoorClosed",
        "message": "[048 T] DOOR_CLOSED: Car C1 closed doors at floor 3",
        "time": 48,
        "car_id": "C1",
        "floor": 3
      },
      {
        "event_type": "PassengerSpawned",
        "message": "[049 T] PASSENGER_SPAWNED: P14 requests 4->0",
        "time": 49,
        "passenger_id": "P14",
        "source": 4,
        "target": 0
      },
      {
        "event_type": "CallRegistered",
        "message": "[049 T] CALL_REGISTERED: Floor 4 requests DOWN",
        "time": 49,
        "floor": 4,
        "direction": -1
      },
      {
        "event_type": "CarMoved",
        "message": "[049 T] CAR_MOVED: Car C1 traveled 3 -> 2",
        "time": 49,
        "car_id": "C1",
        "from_floor": 3,
        "to_floor": 2
      },
      {
        "event_type": "CarArrived",
        "message": "[049 T] CAR_ARRIVED: Car C1 arrived at floor 2",
        "time": 49,
        "car_id": "C1",
        "floor": 2
      },
      {
        "event_type": "DoorOpened",
        "message": "[049 T] DOOR_OPENED: Car C1 opened doors at floor 2",
        "time": 49,
        "car_id": "C1",
        "floor": 2
      },
      {
        "event_type": "PassengerBoarded",
        "message": "[049 T] PASSENGER_BOARDED: P13 boarded car C1 at floor 2",
        "time": 49,
        "passenger_id": "P13",
        "car_id": "C1",
        "floor": 2
      }
    ],
    "metrics": {
      "total_ticks": 49,
      "total_car_moves": 24,
      "passengers_spawned": 14,
      "passengers_completed": 10,
      "avg_wait_time": 4.5,
      "avg_transit_time": 6.9,
      "avg_total_time": 11.4
    }
  },
  "agentic": {
    "events": [
      {
        "event_type": "PassengerSpawned",
        "message": "[002 T] PASSENGER_SPAWNED: P1 requests 3->0",
        "time": 2,
        "passenger_id": "P1",
        "source": 3,
        "target": 0
      },
      {
        "event_type": "CallRegistered",
        "message": "[002 T] CALL_REGISTERED: Floor 3 requests DOWN",
        "time": 2,
        "floor": 3,
        "direction": -1
      },
      {
        "event_type": "PassengerSpawned",
        "message": "[003 T] PASSENGER_SPAWNED: P2 requests 2->0",
        "time": 3,
        "passenger_id": "P2",
        "source": 2,
        "target": 0
      },
      {
        "event_type": "CallRegistered",
        "message": "[003 T] CALL_REGISTERED: Floor 2 requests DOWN",
        "time": 3,
        "floor": 2,
        "direction": -1
      },
      {
        "event_type": "CarMoved",
        "message": "[003 T] CAR_MOVED: Car C1 traveled 0 -> 1",
        "time": 3,
        "car_id": "C1",
        "from_floor": 0,
        "to_floor": 1
      },
      {
        "event_type": "CarMoved",
        "message": "[004 T] CAR_MOVED: Car C1 traveled 1 -> 2",
        "time": 4,
        "car_id": "C1",
        "from_floor": 1,
        "to_floor": 2
      },
      {
        "event_type": "CarMoved",
        "message": "[005 T] CAR_MOVED: Car C1 traveled 2 -> 3",
        "time": 5,
        "car_id": "C1",
        "from_floor": 2,
        "to_floor": 3
      },
      {
        "event_type": "CarArrived",
        "message": "[005 T] CAR_ARRIVED: Car C1 arrived at floor 3 (Decided by Gemini Dispatcher Agent: Prioritizing nearest pending calls to minimize wait time.)",
        "time": 5,
        "car_id": "C1",
        "floor": 3
      },
      {
        "event_type": "DoorOpened",
        "message": "[005 T] DOOR_OPENED: Car C1 opened doors at floor 3",
        "time": 5,
        "car_id": "C1",
        "floor": 3
      },
      {
        "event_type": "PassengerBoarded",
        "message": "[005 T] PASSENGER_BOARDED: P1 boarded car C1 at floor 3",
        "time": 5,
        "passenger_id": "P1",
        "car_id": "C1",
        "floor": 3
      },
      {
        "event_type": "PassengerSpawned",
        "message": "[007 T] PASSENGER_SPAWNED: P3 requests 4->0",
        "time": 7,
        "passenger_id": "P3",
        "source": 4,
        "target": 0
      },
      {
        "event_type": "CallRegistered",
        "message": "[007 T] CALL_REGISTERED: Floor 4 requests DOWN",
        "time": 7,
        "floor": 4,
        "direction": -1
      },
      {
        "event_type": "DoorClosed",
        "message": "[007 T] DOOR_CLOSED: Car C1 closed doors at floor 3",
        "time": 7,
        "car_id": "C1",
        "floor": 3
      },
      {
        "event_type": "PassengerSpawned",
        "message": "[008 T] PASSENGER_SPAWNED: P4 requests 1->0",
        "time": 8,
        "passenger_id": "P4",
        "source": 1,
        "target": 0
      },
      {
        "event_type": "CallRegistered",
        "message": "[008 T] CALL_REGISTERED: Floor 1 requests DOWN",
        "time": 8,
        "floor": 1,
        "direction": -1
      },
      {
        "event_type": "CarMoved",
        "message": "[008 T] CAR_MOVED: Car C1 traveled 3 -> 4",
        "time": 8,
        "car_id": "C1",
        "from_floor": 3,
        "to_floor": 4
      },
      {
        "event_type": "CarArrived",
        "message": "[008 T] CAR_ARRIVED: Car C1 arrived at floor 4 (Decided by Gemini Dispatcher Agent: Prioritizing nearest pending calls to minimize wait time.)",
        "time": 8,
        "car_id": "C1",
        "floor": 4
      },
      {
        "event_type": "DoorOpened",
        "message": "[008 T] DOOR_OPENED: Car C1 opened doors at floor 4",
        "time": 8,
        "car_id": "C1",
        "floor": 4
      },
      {
        "event_type": "PassengerBoarded",
        "message": "[008 T] PASSENGER_BOARDED: P3 boarded car C1 at floor 4",
        "time": 8,
        "passenger_id": "P3",
        "car_id": "C1",
        "floor": 4
      },
      {
        "event_type": "PassengerSpawned",
        "message": "[009 T] PASSENGER_SPAWNED: P5 requests 1->0",
        "time": 9,
        "passenger_id": "P5",
        "source": 1,
        "target": 0
      },
      {
        "event_type": "CallRegistered",
        "message": "[009 T] CALL_REGISTERED: Floor 1 requests DOWN",
        "time": 9,
        "floor": 1,
        "direction": -1
      },
      {
        "event_type": "DoorClosed",
        "message": "[010 T] DOOR_CLOSED: Car C1 closed doors at floor 4",
        "time": 10,
        "car_id": "C1",
        "floor": 4
      },
      {
        "event_type": "CarMoved",
        "message": "[011 T] CAR_MOVED: Car C1 traveled 4 -> 3",
        "time": 11,
        "car_id": "C1",
        "from_floor": 4,
        "to_floor": 3
      },
      {
        "event_type": "CarMoved",
        "message": "[012 T] CAR_MOVED: Car C1 traveled 3 -> 2",
        "time": 12,
        "car_id": "C1",
        "from_floor": 3,
        "to_floor": 2
      },
      {
        "event_type": "CarArrived",
        "message": "[012 T] CAR_ARRIVED: Car C1 arrived at floor 2 (Decided by Gemini Dispatcher Agent: Prioritizing nearest pending calls to minimize wait time.)",
        "time": 12,
        "car_id": "C1",
        "floor": 2
      },
      {
        "event_type": "DoorOpened",
        "message": "[012 T] DOOR_OPENED: Car C1 opened doors at floor 2",
        "time": 12,
        "car_id": "C1",
        "floor": 2
      },
      {
        "event_type": "PassengerBoarded",
        "message": "[012 T] PASSENGER_BOARDED: P2 boarded car C1 at floor 2",
        "time": 12,
        "passenger_id": "P2",
        "car_id": "C1",
        "floor": 2
      },
      {
        "event_type": "DoorClosed",
        "message": "[014 T] DOOR_CLOSED: Car C1 closed doors at floor 2",
        "time": 14,
        "car_id": "C1",
        "floor": 2
      },
      {
        "event_type": "CarMoved",
        "message": "[015 T] CAR_MOVED: Car C1 traveled 2 -> 1",
        "time": 15,
        "car_id": "C1",
        "from_floor": 2,
        "to_floor": 1
      },
      {
        "event_type": "CarArrived",
        "message": "[015 T] CAR_ARRIVED: Car C1 arrived at floor 1 (Decided by Gemini Dispatcher Agent: Prioritizing nearest pending calls to minimize wait time.)",
        "time": 15,
        "car_id": "C1",
        "floor": 1
      },
      {
        "event_type": "DoorOpened",
        "message": "[015 T] DOOR_OPENED: Car C1 opened doors at floor 1",
        "time": 15,
        "car_id": "C1",
        "floor": 1
      },
      {
        "event_type": "PassengerBoarded",
        "message": "[015 T] PASSENGER_BOARDED: P4 boarded car C1 at floor 1",
        "time": 15,
        "passenger_id": "P4",
        "car_id": "C1",
        "floor": 1
      },
      {
        "event_type": "PassengerBoarded",
        "message": "[015 T] PASSENGER_BOARDED: P5 boarded car C1 at floor 1",
        "time": 15,
        "passenger_id": "P5",
        "car_id": "C1",
        "floor": 1
      },
      {
        "event_type": "DoorClosed",
        "message": "[017 T] DOOR_CLOSED: Car C1 closed doors at floor 1",
        "time": 17,
        "car_id": "C1",
        "floor": 1
      },
      {
        "event_type": "PassengerSpawned",
        "message": "[018 T] PASSENGER_SPAWNED: P6 requests 4->0",
        "time": 18,
        "passenger_id": "P6",
        "source": 4,
        "target": 0
      },
      {
        "event_type": "CallRegistered",
        "message": "[018 T] CALL_REGISTERED: Floor 4 requests DOWN",
        "time": 18,
        "floor": 4,
        "direction": -1
      },
      {
        "event_type": "CarMoved",
        "message": "[018 T] CAR_MOVED: Car C1 traveled 1 -> 0",
        "time": 18,
        "car_id": "C1",
        "from_floor": 1,
        "to_floor": 0
      },
      {
        "event_type": "CarArrived",
        "message": "[018 T] CAR_ARRIVED: Car C1 arrived at floor 0 (Decided by Gemini Dispatcher Agent: Prioritizing nearest pending calls to minimize wait time.)",
        "time": 18,
        "car_id": "C1",
        "floor": 0
      },
      {
        "event_type": "DoorOpened",
        "message": "[018 T] DOOR_OPENED: Car C1 opened doors at floor 0",
        "time": 18,
        "car_id": "C1",
        "floor": 0
      },
      {
        "event_type": "PassengerDeboarded",
        "message": "[018 T] PASSENGER_DEBOARDED: P1 exited car C1 at floor 0",
        "time": 18,
        "passenger_id": "P1",
        "car_id": "C1",
        "floor": 0
      },
      {
        "event_type": "PassengerDeboarded",
        "message": "[018 T] PASSENGER_DEBOARDED: P3 exited car C1 at floor 0",
        "time": 18,
        "passenger_id": "P3",
        "car_id": "C1",
        "floor": 0
      },
      {
        "event_type": "PassengerDeboarded",
        "message": "[018 T] PASSENGER_DEBOARDED: P2 exited car C1 at floor 0",
        "time": 18,
        "passenger_id": "P2",
        "car_id": "C1",
        "floor": 0
      },
      {
        "event_type": "PassengerDeboarded",
        "message": "[018 T] PASSENGER_DEBOARDED: P4 exited car C1 at floor 0",
        "time": 18,
        "passenger_id": "P4",
        "car_id": "C1",
        "floor": 0
      },
      {
        "event_type": "PassengerDeboarded",
        "message": "[018 T] PASSENGER_DEBOARDED: P5 exited car C1 at floor 0",
        "time": 18,
        "passenger_id": "P5",
        "car_id": "C1",
        "floor": 0
      },
      {
        "event_type": "PassengerSpawned",
        "message": "[020 T] PASSENGER_SPAWNED: P7 requests 3->0",
        "time": 20,
        "passenger_id": "P7",
        "source": 3,
        "target": 0
      },
      {
        "event_type": "CallRegistered",
        "message": "[020 T] CALL_REGISTERED: Floor 3 requests DOWN",
        "time": 20,
        "floor": 3,
        "direction": -1
      },
      {
        "event_type": "DoorClosed",
        "message": "[020 T] DOOR_CLOSED: Car C1 closed doors at floor 0",
        "time": 20,
        "car_id": "C1",
        "floor": 0
      },
      {
        "event_type": "PassengerSpawned",
        "message": "[021 T] PASSENGER_SPAWNED: P8 requests 4->0",
        "time": 21,
        "passenger_id": "P8",
        "source": 4,
        "target": 0
      },
      {
        "event_type": "CallRegistered",
        "message": "[021 T] CALL_REGISTERED: Floor 4 requests DOWN",
        "time": 21,
        "floor": 4,
        "direction": -1
      },
      {
        "event_type": "CarMoved",
        "message": "[021 T] CAR_MOVED: Car C1 traveled 0 -> 1",
        "time": 21,
        "car_id": "C1",
        "from_floor": 0,
        "to_floor": 1
      },
      {
        "event_type": "PassengerSpawned",
        "message": "[022 T] PASSENGER_SPAWNED: P9 requests 3->0",
        "time": 22,
        "passenger_id": "P9",
        "source": 3,
        "target": 0
      },
      {
        "event_type": "CallRegistered",
        "message": "[022 T] CALL_REGISTERED: Floor 3 requests DOWN",
        "time": 22,
        "floor": 3,
        "direction": -1
      },
      {
        "event_type": "CarMoved",
        "message": "[022 T] CAR_MOVED: Car C1 traveled 1 -> 2",
        "time": 22,
        "car_id": "C1",
        "from_floor": 1,
        "to_floor": 2
      },
      {
        "event_type": "CarMoved",
        "message": "[023 T] CAR_MOVED: Car C1 traveled 2 -> 3",
        "time": 23,
        "car_id": "C1",
        "from_floor": 2,
        "to_floor": 3
      },
      {
        "event_type": "CarArrived",
        "message": "[023 T] CAR_ARRIVED: Car C1 arrived at floor 3 (Decided by Gemini Dispatcher Agent: Prioritizing nearest pending calls to minimize wait time.)",
        "time": 23,
        "car_id": "C1",
        "floor": 3
      },
      {
        "event_type": "DoorOpened",
        "message": "[023 T] DOOR_OPENED: Car C1 opened doors at floor 3",
        "time": 23,
        "car_id": "C1",
        "floor": 3
      },
      {
        "event_type": "PassengerBoarded",
        "message": "[023 T] PASSENGER_BOARDED: P7 boarded car C1 at floor 3",
        "time": 23,
        "passenger_id": "P7",
        "car_id": "C1",
        "floor": 3
      },
      {
        "event_type": "PassengerBoarded",
        "message": "[023 T] PASSENGER_BOARDED: P9 boarded car C1 at floor 3",
        "time": 23,
        "passenger_id": "P9",
        "car_id": "C1",
        "floor": 3
      },
      {
        "event_type": "DoorClosed",
        "message": "[025 T] DOOR_CLOSED: Car C1 closed doors at floor 3",
        "time": 25,
        "car_id": "C1",
        "floor": 3
      },
      {
        "event_type": "CarMoved",
        "message": "[026 T] CAR_MOVED: Car C1 traveled 3 -> 4",
        "time": 26,
        "car_id": "C1",
        "from_floor": 3,
        "to_floor": 4
      },
      {
        "event_type": "CarArrived",
        "message": "[026 T] CAR_ARRIVED: Car C1 arrived at floor 4 (Decided by Gemini Dispatcher Agent: Prioritizing nearest pending calls to minimize wait time.)",
        "time": 26,
        "car_id": "C1",
        "floor": 4
      },
      {
        "event_type": "DoorOpened",
        "message": "[026 T] DOOR_OPENED: Car C1 opened doors at floor 4",
        "time": 26,
        "car_id": "C1",
        "floor": 4
      },
      {
        "event_type": "PassengerBoarded",
        "message": "[026 T] PASSENGER_BOARDED: P6 boarded car C1 at floor 4",
        "time": 26,
        "passenger_id": "P6",
        "car_id": "C1",
        "floor": 4
      },
      {
        "event_type": "PassengerBoarded",
        "message": "[026 T] PASSENGER_BOARDED: P8 boarded car C1 at floor 4",
        "time": 26,
        "passenger_id": "P8",
        "car_id": "C1",
        "floor": 4
      },
      {
        "event_type": "DoorClosed",
        "message": "[028 T] DOOR_CLOSED: Car C1 closed doors at floor 4",
        "time": 28,
        "car_id": "C1",
        "floor": 4
      },
      {
        "event_type": "CarMoved",
        "message": "[029 T] CAR_MOVED: Car C1 traveled 4 -> 3",
        "time": 29,
        "car_id": "C1",
        "from_floor": 4,
        "to_floor": 3
      },
      {
        "event_type": "CarMoved",
        "message": "[030 T] CAR_MOVED: Car C1 traveled 3 -> 2",
        "time": 30,
        "car_id": "C1",
        "from_floor": 3,
        "to_floor": 2
      },
      {
        "event_type": "CarMoved",
        "message": "[031 T] CAR_MOVED: Car C1 traveled 2 -> 1",
        "time": 31,
        "car_id": "C1",
        "from_floor": 2,
        "to_floor": 1
      },
      {
        "event_type": "CarMoved",
        "message": "[032 T] CAR_MOVED: Car C1 traveled 1 -> 0",
        "time": 32,
        "car_id": "C1",
        "from_floor": 1,
        "to_floor": 0
      },
      {
        "event_type": "CarArrived",
        "message": "[032 T] CAR_ARRIVED: Car C1 arrived at floor 0 (Decided by Gemini Dispatcher Agent: Prioritizing nearest pending calls to minimize wait time.)",
        "time": 32,
        "car_id": "C1",
        "floor": 0
      },
      {
        "event_type": "DoorOpened",
        "message": "[032 T] DOOR_OPENED: Car C1 opened doors at floor 0",
        "time": 32,
        "car_id": "C1",
        "floor": 0
      },
      {
        "event_type": "PassengerDeboarded",
        "message": "[032 T] PASSENGER_DEBOARDED: P7 exited car C1 at floor 0",
        "time": 32,
        "passenger_id": "P7",
        "car_id": "C1",
        "floor": 0
      },
      {
        "event_type": "PassengerDeboarded",
        "message": "[032 T] PASSENGER_DEBOARDED: P9 exited car C1 at floor 0",
        "time": 32,
        "passenger_id": "P9",
        "car_id": "C1",
        "floor": 0
      },
      {
        "event_type": "PassengerDeboarded",
        "message": "[032 T] PASSENGER_DEBOARDED: P6 exited car C1 at floor 0",
        "time": 32,
        "passenger_id": "P6",
        "car_id": "C1",
        "floor": 0
      },
      {
        "event_type": "PassengerDeboarded",
        "message": "[032 T] PASSENGER_DEBOARDED: P8 exited car C1 at floor 0",
        "time": 32,
        "passenger_id": "P8",
        "car_id": "C1",
        "floor": 0
      },
      {
        "event_type": "DoorClosed",
        "message": "[034 T] DOOR_CLOSED: Car C1 closed doors at floor 0",
        "time": 34,
        "car_id": "C1",
        "floor": 0
      },
      {
        "event_type": "PassengerSpawned",
        "message": "[035 T] PASSENGER_SPAWNED: P10 requests 2->0",
        "time": 35,
        "passenger_id": "P10",
        "source": 2,
        "target": 0
      },
      {
        "event_type": "CallRegistered",
        "message": "[035 T] CALL_REGISTERED: Floor 2 requests DOWN",
        "time": 35,
        "floor": 2,
        "direction": -1
      },
      {
        "event_type": "CarMoved",
        "message": "[036 T] CAR_MOVED: Car C1 traveled 0 -> 1",
        "time": 36,
        "car_id": "C1",
        "from_floor": 0,
        "to_floor": 1
      },
      {
        "event_type": "CarMoved",
        "message": "[037 T] CAR_MOVED: Car C1 traveled 1 -> 2",
        "time": 37,
        "car_id": "C1",
        "from_floor": 1,
        "to_floor": 2
      },
      {
        "event_type": "CarArrived",
        "message": "[037 T] CAR_ARRIVED: Car C1 arrived at floor 2 (Decided by Gemini Dispatcher Agent: Prioritizing nearest pending calls to minimize wait time.)",
        "time": 37,
        "car_id": "C1",
        "floor": 2
      },
      {
        "event_type": "DoorOpened",
        "message": "[037 T] DOOR_OPENED: Car C1 opened doors at floor 2",
        "time": 37,
        "car_id": "C1",
        "floor": 2
      },
      {
        "event_type": "PassengerBoarded",
        "message": "[037 T] PASSENGER_BOARDED: P10 boarded car C1 at floor 2",
        "time": 37,
        "passenger_id": "P10",
        "car_id": "C1",
        "floor": 2
      },
      {
        "event_type": "DoorClosed",
        "message": "[039 T] DOOR_CLOSED: Car C1 closed doors at floor 2",
        "time": 39,
        "car_id": "C1",
        "floor": 2
      },
      {
        "event_type": "CarMoved",
        "message": "[040 T] CAR_MOVED: Car C1 traveled 2 -> 1",
        "time": 40,
        "car_id": "C1",
        "from_floor": 2,
        "to_floor": 1
      },
      {
        "event_type": "CarMoved",
        "message": "[041 T] CAR_MOVED: Car C1 traveled 1 -> 0",
        "time": 41,
        "car_id": "C1",
        "from_floor": 1,
        "to_floor": 0
      },
      {
        "event_type": "CarArrived",
        "message": "[041 T] CAR_ARRIVED: Car C1 arrived at floor 0 (Decided by Gemini Dispatcher Agent: Prioritizing nearest pending calls to minimize wait time.)",
        "time": 41,
        "car_id": "C1",
        "floor": 0
      },
      {
        "event_type": "DoorOpened",
        "message": "[041 T] DOOR_OPENED: Car C1 opened doors at floor 0",
        "time": 41,
        "car_id": "C1",
        "floor": 0
      },
      {
        "event_type": "PassengerDeboarded",
        "message": "[041 T] PASSENGER_DEBOARDED: P10 exited car C1 at floor 0",
        "time": 41,
        "passenger_id": "P10",
        "car_id": "C1",
        "floor": 0
      },
      {
        "event_type": "PassengerSpawned",
        "message": "[043 T] PASSENGER_SPAWNED: P11 requests 3->0",
        "time": 43,
        "passenger_id": "P11",
        "source": 3,
        "target": 0
      },
      {
        "event_type": "CallRegistered",
        "message": "[043 T] CALL_REGISTERED: Floor 3 requests DOWN",
        "time": 43,
        "floor": 3,
        "direction": -1
      },
      {
        "event_type": "DoorClosed",
        "message": "[043 T] DOOR_CLOSED: Car C1 closed doors at floor 0",
        "time": 43,
        "car_id": "C1",
        "floor": 0
      },
      {
        "event_type": "PassengerSpawned",
        "message": "[044 T] PASSENGER_SPAWNED: P12 requests 3->0",
        "time": 44,
        "passenger_id": "P12",
        "source": 3,
        "target": 0
      },
      {
        "event_type": "CallRegistered",
        "message": "[044 T] CALL_REGISTERED: Floor 3 requests DOWN",
        "time": 44,
        "floor": 3,
        "direction": -1
      },
      {
        "event_type": "CarMoved",
        "message": "[044 T] CAR_MOVED: Car C1 traveled 0 -> 1",
        "time": 44,
        "car_id": "C1",
        "from_floor": 0,
        "to_floor": 1
      },
      {
        "event_type": "CarMoved",
        "message": "[045 T] CAR_MOVED: Car C1 traveled 1 -> 2",
        "time": 45,
        "car_id": "C1",
        "from_floor": 1,
        "to_floor": 2
      },
      {
        "event_type": "CarMoved",
        "message": "[046 T] CAR_MOVED: Car C1 traveled 2 -> 3",
        "time": 46,
        "car_id": "C1",
        "from_floor": 2,
        "to_floor": 3
      },
      {
        "event_type": "CarArrived",
        "message": "[046 T] CAR_ARRIVED: Car C1 arrived at floor 3 (Decided by Gemini Dispatcher Agent: Prioritizing nearest pending calls to minimize wait time.)",
        "time": 46,
        "car_id": "C1",
        "floor": 3
      },
      {
        "event_type": "DoorOpened",
        "message": "[046 T] DOOR_OPENED: Car C1 opened doors at floor 3",
        "time": 46,
        "car_id": "C1",
        "floor": 3
      },
      {
        "event_type": "PassengerBoarded",
        "message": "[046 T] PASSENGER_BOARDED: P11 boarded car C1 at floor 3",
        "time": 46,
        "passenger_id": "P11",
        "car_id": "C1",
        "floor": 3
      },
      {
        "event_type": "PassengerBoarded",
        "message": "[046 T] PASSENGER_BOARDED: P12 boarded car C1 at floor 3",
        "time": 46,
        "passenger_id": "P12",
        "car_id": "C1",
        "floor": 3
      },
      {
        "event_type": "PassengerSpawned",
        "message": "[047 T] PASSENGER_SPAWNED: P13 requests 2->0",
        "time": 47,
        "passenger_id": "P13",
        "source": 2,
        "target": 0
      },
      {
        "event_type": "CallRegistered",
        "message": "[047 T] CALL_REGISTERED: Floor 2 requests DOWN",
        "time": 47,
        "floor": 2,
        "direction": -1
      },
      {
        "event_type": "DoorClosed",
        "message": "[048 T] DOOR_CLOSED: Car C1 closed doors at floor 3",
        "time": 48,
        "car_id": "C1",
        "floor": 3
      },
      {
        "event_type": "PassengerSpawned",
        "message": "[049 T] PASSENGER_SPAWNED: P14 requests 4->0",
        "time": 49,
        "passenger_id": "P14",
        "source": 4,
        "target": 0
      },
      {
        "event_type": "CallRegistered",
        "message": "[049 T] CALL_REGISTERED: Floor 4 requests DOWN",
        "time": 49,
        "floor": 4,
        "direction": -1
      },
      {
        "event_type": "CarMoved",
        "message": "[049 T] CAR_MOVED: Car C1 traveled 3 -> 2",
        "time": 49,
        "car_id": "C1",
        "from_floor": 3,
        "to_floor": 2
      },
      {
        "event_type": "CarArrived",
        "message": "[049 T] CAR_ARRIVED: Car C1 arrived at floor 2 (Decided by Gemini Dispatcher Agent: Prioritizing nearest pending calls to minimize wait time.)",
        "time": 49,
        "car_id": "C1",
        "floor": 2
      },
      {
        "event_type": "DoorOpened",
        "message": "[049 T] DOOR_OPENED: Car C1 opened doors at floor 2",
        "time": 49,
        "car_id": "C1",
        "floor": 2
      },
      {
        "event_type": "PassengerBoarded",
        "message": "[049 T] PASSENGER_BOARDED: P13 boarded car C1 at floor 2",
        "time": 49,
        "passenger_id": "P13",
        "car_id": "C1",
        "floor": 2
      }
    ],
    "metrics": {
      "total_ticks": 49,
      "total_car_moves": 24,
      "passengers_spawned": 14,
      "passengers_completed": 10,
      "avg_wait_time": 4.5,
      "avg_transit_time": 6.9,
      "avg_total_time": 11.4
    }
  }
}